<package>
  <description brief="wam_controllers">

     wam_controllers

  </description>
  <author>jkizito</author>
  <license>BSD</license>
  <review status="unreviewed" notes=""/>
  <url>http://ros.org/wiki/wam_controllers</url>
  <depend package="roscpp"/>
  <depend package="rospy"/>
  <depend package="wam_srvs"/>
  <depend package="rostest"/>
  <depend package="rosunit"/>
  <depend package="actionlib"/>
  <depend package="control_msgs"/>
  <depend package="sensor_msgs"/>
  <depend package="trajectory_msgs"/>
  <depend package="pr2_mechanism_msgs"/>
  <depend package="pr2_controllers_msgs"/>

</package>


